semux/__init__.py
semux/encoding.py
semux/hash.py
semux/key.py
semux/signature.py
semux-0.0.1.dist-info/DESCRIPTION.rst
semux-0.0.1.dist-info/METADATA
semux-0.0.1.dist-info/RECORD
semux-0.0.1.dist-info/WHEEL
semux-0.0.1.dist-info/metadata.json
semux-0.0.1.dist-info/top_level.txt
