Metadata-Version: 2.0
Name: semux
Version: 0.0.1
Summary: UNKNOWN
Home-page: https://github.com/gpip/semux-py
Author: UNKNOWN
Author-email: UNKNOWN
License: UNKNOWN
Platform: UNKNOWN
Requires-Dist: PyNaCl (==1.2.1)
Requires-Dist: pyblake2 (==1.1.2)
